skops/__init__.py
skops/conftest.py
skops/card/__init__.py
skops/card/_markup.py
skops/card/_model_card.py
skops/card/_parser.py
skops/card/_templates.py
skops/card/default_template.md
skops/card/tests/test_card.py
skops/card/tests/test_parser.py
skops/card/tests/examples/bert-base-uncased.md
skops/card/tests/examples/bert-base-uncased.md.diff
skops/card/tests/examples/clip-vit-large-patch14.md
skops/card/tests/examples/clip-vit-large-patch14.md.diff
skops/card/tests/examples/gpt2.md
skops/card/tests/examples/gpt2.md.diff
skops/card/tests/examples/specter.md
skops/card/tests/examples/specter.md.diff
skops/card/tests/examples/toy-example.md
skops/card/tests/examples/toy-example.md.diff
skops/card/tests/examples/vit-base-patch32-224-in21k.md
skops/card/tests/examples/vit-base-patch32-224-in21k.md.diff
skops/cli/__init__.py
skops/cli/_convert.py
skops/cli/_update.py
skops/cli/_utils.py
skops/cli/entrypoint.py
skops/cli/tests/test_cli_utils.py
skops/cli/tests/test_convert.py
skops/cli/tests/test_entrypoint.py
skops/cli/tests/test_update.py
skops/io/__init__.py
skops/io/_audit.py
skops/io/_general.py
skops/io/_numpy.py
skops/io/_persist.py
skops/io/_protocol.py
skops/io/_quantile_forest.py
skops/io/_scipy.py
skops/io/_sklearn.py
skops/io/_trusted_types.py
skops/io/_utils.py
skops/io/_visualize.py
skops/io/exceptions.py
skops/io/old/_general_v0.py
skops/io/old/_numpy_v0.py
skops/io/old/_numpy_v1.py
skops/io/tests/_utils.py
skops/io/tests/test_audit.py
skops/io/tests/test_external.py
skops/io/tests/test_persist.py
skops/io/tests/test_persist_old.py
skops/io/tests/test_utils.py
skops/io/tests/test_visualize.py
skops/utils/__init__.py
skops/utils/_fixes.py
skops/utils/importutils.py
skops/utils/tests/test_importutils.py
skops-0.12.0.dist-info/METADATA
skops-0.12.0.dist-info/WHEEL
skops-0.12.0.dist-info/licenses/LICENSE
skops-0.12.0.dist-info/RECORD
