Metadata-Version: 2.4
Name: skops
Version: 0.12.0
Summary: A set of tools, related to machine learning in production.
Project-URL: Homepage, http://github.com/skops-dev/skops
Project-URL: Documentation, https://skops.readthedocs.io/en/stable/
Project-URL: Repository, http://github.com/skops-dev/skops
Project-URL: Issues, http://github.com/skops-dev/skops/issues
Project-URL: Changelog, https://skops.readthedocs.io/en/stable/changes.html
Maintainer-email: Adrin Jalali <adrin.jalali@gmail.com>, Benjamin Bossan <benjamin.bossan@gmail.com>
License: The MIT License (MIT)
License-File: LICENSE
Classifier: Development Status :: 1 - Planning
Classifier: Intended Audience :: Developers
Classifier: Intended Audience :: Science/Research
Classifier: License :: OSI Approved
Classifier: Operating System :: MacOS
Classifier: Operating System :: Microsoft :: Windows
Classifier: Operating System :: POSIX
Classifier: Operating System :: Unix
Classifier: Programming Language :: Python
Classifier: Programming Language :: Python :: 3
Classifier: Programming Language :: Python :: 3.9
Classifier: Programming Language :: Python :: 3.10
Classifier: Programming Language :: Python :: 3.11
Classifier: Programming Language :: Python :: 3.12
Classifier: Programming Language :: Python :: 3.13
Classifier: Programming Language :: Python :: Implementation :: CPython
Classifier: Topic :: Scientific/Engineering
Classifier: Topic :: Software Development
Requires-Python: >=3.9
Requires-Dist: numpy>=1.25.0
Requires-Dist: packaging>=17.0
Requires-Dist: prettytable>=3.9
Requires-Dist: scikit-learn>=1.2
Requires-Dist: scipy>=1.10.0
Provides-Extra: rich
Requires-Dist: rich>=12; extra == 'rich'
